pysweetcat/__init__.py
pysweetcat/config.py
pysweetcat/pysweetcat.py
pySWEETCat-1.1.1.dist-info/LICENSE
pySWEETCat-1.1.1.dist-info/METADATA
pySWEETCat-1.1.1.dist-info/WHEEL
pySWEETCat-1.1.1.dist-info/top_level.txt
pySWEETCat-1.1.1.dist-info/RECORD
