Metadata-Version: 2.1
Name: pySWEETCat
Version: 1.1.1
Summary: A pure-Python package to download data from SWEET-Cat
Author-email: João Faria <joao.faria@unige.ch>
License: MIT
Project-URL: Homepage, https://github.com/j-faria/pWEETCat
Project-URL: Repository, https://github.com/j-faria/pySWEETCat
Project-URL: Issues, https://github.com/j-faria/pySWEETCat/issues
Classifier: Programming Language :: Python :: 3
Requires-Python: >=3.7
License-File: LICENSE
